TravelAlerts_sbubiloctech/AnalyzeTravelAlerts.py
TravelAlerts_sbubiloctech/TravelAlert.py
TravelAlerts_sbubiloctech/TravelAlertClassifier.py
TravelAlerts_sbubiloctech/TravelAlertsAnalysis.py
TravelAlerts_sbubiloctech/__init__.py
TravelAlerts_sbubiloctech-0.1.0.dist-info/LICENSE
TravelAlerts_sbubiloctech-0.1.0.dist-info/METADATA
TravelAlerts_sbubiloctech-0.1.0.dist-info/WHEEL
TravelAlerts_sbubiloctech-0.1.0.dist-info/top_level.txt
TravelAlerts_sbubiloctech-0.1.0.dist-info/RECORD
