Metadata-Version: 2.1
Name: TravelAlerts_sbubiloctech
Version: 0.1.0
Summary: Package to read, analyze and classify travel advisories by country on the U.S. State Department website
Author-email: "Sunil Baliga (Ubiloc Technologies LLC)" <technical_sb@ubiloctech.com>
Maintainer-email: "Sunil Baliga (Ubiloc Technologies LLC)" <technical_sb@ubiloctech.com>
License: GNU Free Documentation License
Project-URL: Repositories, https://github.com/sbubiloctech/travelalerts
Keywords: advisories,scraping,parsing,U.S. State Department,classification,analysis
Classifier: Programming Language :: Python :: 3.9
Classifier: Operating System :: OS Independent
Classifier: Development Status :: 2 - Pre-Alpha
Classifier: Topic :: Games/Entertainment :: Simulation
Requires-Python: >=3.9
License-File: LICENSE
Requires-Dist: nltk >=3.8.1
Requires-Dist: requests >=2.31.0
Requires-Dist: beautifulsoup4 >=4.12.3
Requires-Dist: numpy >=1.26.0
Requires-Dist: pandas >=2.1.1
Requires-Dist: asyncio >=3.4.3
Requires-Dist: aiohttp >=3.10.5
Requires-Dist: tqdm >=4.66.5
Requires-Dist: pytest >=8.3.2
